{
  "type": "FeatureCollection",
  "name": "BBMP Wards",
  "crs": {
    "type": "name",
    "properties": {
      "name": "urn:ogc:def:crs:OGC:1.3:CRS84"
    }
  },
  "features": [
    {
      "type": "Feature",
      "properties": {
        "letter": "G",
        "address": "No.9, 1st Cross Rd, Shankarapura, Bengaluru, Karnataka 560004",
        "category": "Important Medical Services",
        "cityName": "bengaluru",
        "icon": "./assets/Icons/coronavirus-testingcentre.png",
        "id": 9840,
        "lat": 12.953276,
        "lng": 77.567093,
        "menuId": 93,
        "name": "Cancyte",
        "phone": "080 4131 1877",
        "subcategory": "Corona Testing Centre",
        "total": 1,
        "type": "12"
      },
      "geometry": {
        "type": "Point",
        "coordinates": [73.821028, 18.621819]
      }
    },
    {
      "type": "Feature",
      "properties": {
        "letter": "G",
        "address": "No.9, 1st Cross Rd, Shankarapura, Bengaluru, Karnataka 560004",
        "category": "Important Medical Services",
        "cityName": "bengaluru",
        "icon": "./assets/Icons/coronavirus-testingcentre.png",
        "id": 9839,
        "lat": 12.982099,
        "lng": 77.601612,
        "menuId": 93,
        "name": "Neuberg Anand Reference Laboratory",
        "phone": "1800 425 1974",
        "subcategory": "Corona Testing Centre",
        "total": 1,
        "type": "12"
      },
      "geometry": {
        "type": "Point",
        "coordinates": [77.601612, 12.982099]
      }
    }
  ]
}
